borsapy/__init__.py
borsapy/backtest.py
borsapy/bond.py
borsapy/cache.py
borsapy/calendar.py
borsapy/charts.py
borsapy/crypto.py
borsapy/eurobond.py
borsapy/exceptions.py
borsapy/fund.py
borsapy/fx.py
borsapy/index.py
borsapy/inflation.py
borsapy/market.py
borsapy/multi.py
borsapy/portfolio.py
borsapy/replay.py
borsapy/scanner.py
borsapy/screener.py
borsapy/search.py
borsapy/stream.py
borsapy/tcmb.py
borsapy/technical.py
borsapy/ticker.py
borsapy/viop.py
borsapy/_models/__init__.py
borsapy/_providers/__init__.py
borsapy/_providers/base.py
borsapy/_providers/bist_index.py
borsapy/_providers/btcturk.py
borsapy/_providers/canlidoviz.py
borsapy/_providers/dovizcom.py
borsapy/_providers/dovizcom_calendar.py
borsapy/_providers/dovizcom_tahvil.py
borsapy/_providers/hedeffiyat.py
borsapy/_providers/isin.py
borsapy/_providers/isyatirim.py
borsapy/_providers/isyatirim_screener.py
borsapy/_providers/kap.py
borsapy/_providers/kap_holdings.py
borsapy/_providers/pine_facade.py
borsapy/_providers/tcmb.py
borsapy/_providers/tcmb_rates.py
borsapy/_providers/tefas.py
borsapy/_providers/tradingview.py
borsapy/_providers/tradingview_etf.py
borsapy/_providers/tradingview_scanner.py
borsapy/_providers/tradingview_screener_native.py
borsapy/_providers/tradingview_search.py
borsapy/_providers/viop.py
borsapy/_providers/ziraat_eurobond.py
borsapy/cli/__init__.py
borsapy/cli/app.py
borsapy/cli/formatters.py
borsapy/cli/utils.py
borsapy/cli/commands/__init__.py
borsapy/cli/commands/auth.py
borsapy/cli/commands/bonds.py
borsapy/cli/commands/companies.py
borsapy/cli/commands/compare.py
borsapy/cli/commands/dividends.py
borsapy/cli/commands/economic.py
borsapy/cli/commands/eurobond.py
borsapy/cli/commands/financials.py
borsapy/cli/commands/fund.py
borsapy/cli/commands/fx_rates.py
borsapy/cli/commands/history.py
borsapy/cli/commands/holders.py
borsapy/cli/commands/index_cmd.py
borsapy/cli/commands/inflation.py
borsapy/cli/commands/news.py
borsapy/cli/commands/price.py
borsapy-0.7.2.dist-info/METADATA
borsapy-0.7.2.dist-info/WHEEL
borsapy-0.7.2.dist-info/entry_points.txt
borsapy-0.7.2.dist-info/licenses/LICENSE
borsapy-0.7.2.dist-info/RECORD
