Metadata-Version: 2.4
Name: borsapy
Version: 0.7.2
Summary: Turkish financial markets data library - yfinance-like API for BIST stocks, forex, crypto, and more
Project-URL: Homepage, https://github.com/saidsurucu/borsapy
Project-URL: Documentation, https://github.com/saidsurucu/borsapy#readme
Project-URL: Repository, https://github.com/saidsurucu/borsapy
Project-URL: Issues, https://github.com/saidsurucu/borsapy/issues
Author: Said Surucu
License: Apache-2.0
License-File: LICENSE
Keywords: bist,crypto,finance,forex,market-data,stocks,turkey
Classifier: Development Status :: 3 - Alpha
Classifier: Intended Audience :: Developers
Classifier: Intended Audience :: Financial and Insurance Industry
Classifier: License :: OSI Approved :: Apache Software License
Classifier: Operating System :: OS Independent
Classifier: Programming Language :: Python :: 3
Classifier: Programming Language :: Python :: 3.10
Classifier: Programming Language :: Python :: 3.11
Classifier: Programming Language :: Python :: 3.12
Classifier: Topic :: Office/Business :: Financial :: Investment
Requires-Python: >=3.10
Requires-Dist: beautifulsoup4>=4.12.0
Requires-Dist: httpx>=0.27.0
Requires-Dist: lxml>=5.0.0
Requires-Dist: openai>=1.0.0
Requires-Dist: openpyxl>=3.1.0
Requires-Dist: pandas>=2.0.0
Requires-Dist: pydantic>=2.0.0
Requires-Dist: pymupdf4llm>=0.2.9
Requires-Dist: rich>=13.0.0
Requires-Dist: tradingview-screener>=3.0.0
Requires-Dist: typer>=0.12.0
Requires-Dist: urllib3>=2.0.0
Requires-Dist: websocket-client>=1.9.0
Provides-Extra: dev
Requires-Dist: pytest-cov>=4.0.0; extra == 'dev'
Requires-Dist: pytest>=7.0.0; extra == 'dev'
Requires-Dist: ruff>=0.1.0; extra == 'dev'
